setup.py
weatherman.py
weatherman.egg-info/PKG-INFO
weatherman.egg-info/SOURCES.txt
weatherman.egg-info/dependency_links.txt
weatherman.egg-info/entry_points.txt
weatherman.egg-info/requires.txt
weatherman.egg-info/top_level.txt