Metadata-Version: 1.0
Name: weatherman
Version: 0.17
Summary: Elastic Beanstalk Stack Launcher
Home-page: https://github.com/ethanmcc/weatherman
Author: Ethan McCreadie
Author-email: ethanmcc@gmail.com
License: UNKNOWN
Platform: UNKNOWN
